streamxml2json/__init__.py
streamxml2json-1.0.1.dist-info/LICENSE
streamxml2json-1.0.1.dist-info/METADATA
streamxml2json-1.0.1.dist-info/WHEEL
streamxml2json-1.0.1.dist-info/top_level.txt
streamxml2json-1.0.1.dist-info/RECORD
