Metadata-Version: 2.1
Name: streamxml2json
Version: 1.0.1
Summary: Simple library to stream a huge XML file to a JSON file
Home-page: https://github.com/rafaeelaudibert/streamxml2json
Author: RafaAudibert
Author-email: rafaeelaudibert@gmail.com
License: MIT
Platform: UNKNOWN
Classifier: License :: OSI Approved :: MIT License
Classifier: Programming Language :: Python :: 3
Classifier: Programming Language :: Python :: 3.2
Classifier: Programming Language :: Python :: 3.3
Classifier: Programming Language :: Python :: 3.4
Classifier: Programming Language :: Python :: 3.5
Classifier: Programming Language :: Python :: 3.6
Classifier: Programming Language :: Python :: 3.7
Classifier: Programming Language :: Python :: 3.8
Classifier: Programming Language :: Python :: 3.9
Classifier: Programming Language :: Python :: 3.10
Classifier: Programming Language :: Python :: Implementation :: CPython
Classifier: Programming Language :: Python :: Implementation :: PyPy
License-File: LICENSE
Requires-Dist: simplejson
Requires-Dist: jsonstreams
Requires-Dist: xmltodict
Requires-Dist: tqdm
